{
  "display": {
    "name": {
      "translate": "modifier.forbidden_arcanus.fiery"
    },
    "texture": "forbidden_arcanus:textures/gui/tooltip/fiery.png",
    "tooltip_color": {
      "end": -11008506,
      "start": -28928
    }
  },
  "incompatible_enchantments": "#forbidden_arcanus:modifier/fiery_incompatible",
  "incompatible_items": "#forbidden_arcanus:modifier/fiery_incompatible",
  "predicate": {
    "predicates": {
      "valhelsia_core:any_of": {
        "neoforge:item_ability": [
          "pickaxe_dig",
          "axe_dig",
          "shovel_dig",
          "hoe_dig"
        ]
      }
    }
  }
}